LICENSE
README.md
setup.py
pyioapi/__init__.py
pyioapi/io.py
pyioapi/read_girddesc.py
pyioapi/util.py
pyioapi.egg-info/PKG-INFO
pyioapi.egg-info/SOURCES.txt
pyioapi.egg-info/dependency_links.txt
pyioapi.egg-info/entry_points.txt
pyioapi.egg-info/top_level.txt
test/__init__.py
test/test_backend.py